MANIFEST.in
README.md
setup.py
buty_phyl/__init__.py
buty_phyl/__main__.py
buty_phyl.egg-info/PKG-INFO
buty_phyl.egg-info/SOURCES.txt
buty_phyl.egg-info/dependency_links.txt
buty_phyl.egg-info/entry_points.txt
buty_phyl.egg-info/top_level.txt
buty_phyl/data/.DS_Store
buty_phyl/data/.Rhistory
buty_phyl/data/Complete_genome_16S.fasta
buty_phyl/data/GMC_CG_16S.fasta
buty_phyl/data/GMC_CG_16S.fasta.all.V4_V5.fasta
buty_phyl/data/GMC_CG_AHR_2path.txt
buty_phyl/data/GMC_CG_AHR_gene_3ofpath.txt
buty_phyl/data/GMC_CG_AHR_gene_3ofpks.txt
buty_phyl/data/GMC_CG_buk_ptbORbut.V4_V5.txt
buty_phyl/data/GMC_CG_buk_ptbORbut.txt
buty_phyl/data/GMC_CG_napORnar_nir.txt
buty_phyl/data/GMC_CG_pathogen.V4_V5.txt
buty_phyl/data/GMC_CG_pathogen.txt
buty_phyl/data/GMC_CG_sat_apr_dsr.txt
buty_phyl/data/GMC_CG_species.V4_V5.txt
buty_phyl/data/GMC_CG_species.txt
buty_phyl/data/Genome_NR.txt
buty_phyl/data/Genome_NR_nap_nar.txt
buty_phyl/data/Genome_NR_nir.txt
buty_phyl/data/Genome_SRB.txt
buty_phyl/data/Genome_SRB_SAT.txt
buty_phyl/data/Genome_SRB_apr.txt
buty_phyl/data/Genome_SRB_dsr_dsv.txt
buty_phyl/example/example.otu_seqs
buty_phyl/example/example.otu_table
buty_phyl/scripts/.DS_Store
buty_phyl/scripts/Bayers.model.py
buty_phyl/scripts/Bayers.model.species.py
buty_phyl/scripts/OTU.filter.py
buty_phyl/scripts/Predict.summary.py
buty_phyl/scripts/inferTraits.py
buty_phyl/scripts/inferTraits_species.py
buty_phyl/scripts/treeformat.py