Metadata-Version: 2.1
Name: buty-phyl
Version: 1.0.7
Summary: Inferring traits by 16S
Home-page: https://github.com/caozhichongchong/BayersTraits_16S
Author: Anni Zhang
Author-email: anniz44@mit.edu
License: MIT
Keywords: 16S,bacterial genomes,function,traits
Platform: UNKNOWN
Classifier: Programming Language :: Python :: 3
